byted_overpass_ad_cc_dpa_sofa_internal_i18n/__init__.py
byted_overpass_ad_cc_dpa_sofa_internal_i18n-0.0.1.dist-info/METADATA
byted_overpass_ad_cc_dpa_sofa_internal_i18n-0.0.1.dist-info/WHEEL
byted_overpass_ad_cc_dpa_sofa_internal_i18n-0.0.1.dist-info/top_level.txt
byted_overpass_ad_cc_dpa_sofa_internal_i18n-0.0.1.dist-info/RECORD
